[
	{
		"icon": "/images/1494.png",
		"name": "乌酱",
		"time": "03-16",
		"play": "1220",
		"title": "特别预告 |「女武神的餐桌」动画第二季，今年暑期开饭！",
		"img": "/img/xiyang.jpg",
		"support": 10,
		"talk": 5,
		"share": 2
	},
	{
		"icon": "/images/1494.png",
		"name": "乌酱",
		"time": "03-16",
		"play": "1220",
		"title": "特别预告 |「女武神的餐桌」动画第二季，今年暑期开饭！",
		"img": "/img/xiyang.jpg",
		"support": 10,
		"talk": 5,
		"share": 2
	},
	{
		"icon": "/images/1494.png",
		"name": "乌酱",
		"time": "03-16",
		"play": "1220",
		"title": "新服装情报丨真红骑士·月蚀服装「椿与黑檀」即将登场！",
		"img": "/img/xiyang.jpg",
		"support": 10,
		"talk": 5,
		"share": 2
	},
	{
		"icon": "/images/1494.png",
		"name": "乌酱",
		"time": "03-16",
		"play": "1220",
		"title": "新服装情报丨真红骑士·月蚀服装「椿与黑檀」即将登场！",
		"img": "/img/xiyang.jpg",
		"support": 10,
		"talk": 5,
		"share": 2
	},
	{
		"icon": "/images/1494.png",
		"name": "乌酱",
		"time": "03-16",
		"play": "1220",
		"title": "奥托讲堂丨SP角色「朔夜观星」登场，千年思念，寄往星辰。",
		"img": "/img/xiyang.jpg",
		"support": 10,
		"talk": 5,
		"share": 2
	},
	{
		"icon": "/images/1494.png",
		"name": "乌酱",
		"time": "03-16",
		"play": "1220",
		"title": "奥托讲堂丨SP角色「朔夜观星」登场，千年思念，寄往星辰。",
		"img": "/img/xiyang.jpg",
		"support": 10,
		"talk": 4,
		"share": 2
	}
]